{
    "prepare_queue": {
        "installed": [],
        "uninstalled": []
    },
    "config_munge": {
        "files": {}
    },
    "installed_plugins": {
        "cordova-plugin-whitelist": {
            "PACKAGE_NAME": "fr.louisbl.cordova.tests.locationservices"
        },
        "cordova-plugin-locationservices": {
            "PACKAGE_NAME": "fr.louisbl.cordova.tests.locationservices"
        },
        "cordova-plugin-test-framework": {
            "PACKAGE_NAME": "fr.louisbl.cordova.tests.locationservices"
        },
        "cordova-plugin-locationservices-tests": {
            "PACKAGE_NAME": "fr.louisbl.cordova.tests.locationservices"
        }
    },
    "dependent_plugins": {}
}